cfc/__init__.py
cfc/app.py
cfc/auth.py
cfc/config.py
cfc/environment.py
contactsoftware_functions_client-0.5.4.dist-info/LICENSE
contactsoftware_functions_client-0.5.4.dist-info/METADATA
contactsoftware_functions_client-0.5.4.dist-info/WHEEL
contactsoftware_functions_client-0.5.4.dist-info/entry_points.txt
contactsoftware_functions_client-0.5.4.dist-info/RECORD
