Metadata-Version: 2.3
Name: contactsoftware-functions-client
Version: 0.5.4
Summary: Client for uploading and managing Functions in CIM Database Cloud.
License: MIT
Author: Jens Kürten
Author-email: jku@contact.de
Requires-Python: >=3.10,<4
Classifier: License :: OSI Approved :: MIT License
Classifier: Programming Language :: Python :: 3
Classifier: Programming Language :: Python :: 3.10
Classifier: Programming Language :: Python :: 3.11
Classifier: Programming Language :: Python :: 3.12
Classifier: Programming Language :: Python :: 3.13
Requires-Dist: PyYAML (>=6.0)
Requires-Dist: appdirs (>=1.4.4)
Requires-Dist: click (>=8.0.4,<8.2.0)
Requires-Dist: requests (>=2.20.0,<3.0.0)
Requires-Dist: rich (>=12.0.1)
Requires-Dist: typer (>=0.15.3)
Requires-Dist: urllib3 (>=1.26.16)
